[
  {
    "Name": "EUR",
    "Base": "USD",
    "Value": 0.90535
  },
  {
    "Name": "TRY",
    "Base": "USD",
    "Value": 29.60612
  },
  {
    "Name": "SAR",
    "Base": "USD",
    "Value": 3.75
  },
  {
    "Name": "NOK",
    "Base": "USD",
    "Value": 10.15995
  },
  {
    "Name": "JPY",
    "Base": "USD",
    "Value": 140.89100000000002
  },
  {
    "Name": "HUF",
    "Base": "USD",
    "Value": 346.58000000000004
  },
  {
    "Name": "CZK",
    "Base": "USD",
    "Value": 22.3805
  },
  {
    "Name": "CAD",
    "Base": "USD",
    "Value": 1.3249499999999999
  },
  {
    "Name": "PLN",
    "Base": "USD",
    "Value": 5.110747
  }
]