[
  {
    "Name": "EUR",
    "Base": "USD",
    "Value": 0.9115949999999999
  },
  {
    "Name": "TRY",
    "Base": "USD",
    "Value": 30.079000000000004
  },
  {
    "Name": "SAR",
    "Base": "USD",
    "Value": 3.75074
  },
  {
    "Name": "NOK",
    "Base": "USD",
    "Value": 10.26791
  },
  {
    "Name": "JPY",
    "Base": "USD",
    "Value": 144.70350000000002
  },
  {
    "Name": "HUF",
    "Base": "USD",
    "Value": 345.55
  },
  {
    "Name": "CZK",
    "Base": "USD",
    "Value": 22.5176
  },
  {
    "Name": "CAD",
    "Base": "USD",
    "Value": 1.33798
  },
  {
    "Name": "PLN",
    "Base": "USD",
    "Value": 3.970077
  }
]