[
  {
    "Name": "EUR",
    "Base": "USD",
    "Value": 0.9308299999999999
  },
  {
    "Name": "TRY",
    "Base": "USD",
    "Value": 32.3768
  },
  {
    "Name": "SAR",
    "Base": "USD",
    "Value": 3.7505469999999996
  },
  {
    "Name": "NOK",
    "Base": "USD",
    "Value": 10.686200000000001
  },
  {
    "Name": "JPY",
    "Base": "USD",
    "Value": 157.186
  },
  {
    "Name": "HUF",
    "Base": "USD",
    "Value": 367.83000000000004
  },
  {
    "Name": "CZK",
    "Base": "USD",
    "Value": 23.020000000000003
  },
  {
    "Name": "CAD",
    "Base": "USD",
    "Value": 1.374735
  },
  {
    "Name": "PLN",
    "Base": "USD",
    "Value": 4.0404029999999995
  }
]