[
  {
    "Name": "EUR",
    "Base": "USD",
    "Value": 0.91975
  },
  {
    "Name": "TRY",
    "Base": "USD",
    "Value": 32.229400000000005
  },
  {
    "Name": "SAR",
    "Base": "USD",
    "Value": 3.7504939999999998
  },
  {
    "Name": "NOK",
    "Base": "USD",
    "Value": 10.576300000000002
  },
  {
    "Name": "JPY",
    "Base": "USD",
    "Value": 156.084
  },
  {
    "Name": "HUF",
    "Base": "USD",
    "Value": 359.42
  },
  {
    "Name": "CZK",
    "Base": "USD",
    "Value": 22.656100000000002
  },
  {
    "Name": "CAD",
    "Base": "USD",
    "Value": 1.36985
  },
  {
    "Name": "PLN",
    "Base": "USD",
    "Value": 3.9497769999999996
  }
]