[
  {
    "Name": "EUR",
    "Base": "USD",
    "Value": 0.9244549999999999
  },
  {
    "Name": "TRY",
    "Base": "USD",
    "Value": 32.701060000000005
  },
  {
    "Name": "SAR",
    "Base": "USD",
    "Value": 3.75149
  },
  {
    "Name": "NOK",
    "Base": "USD",
    "Value": 10.553500000000001
  },
  {
    "Name": "JPY",
    "Base": "USD",
    "Value": 160.746
  },
  {
    "Name": "HUF",
    "Base": "USD",
    "Value": 362.8
  },
  {
    "Name": "CZK",
    "Base": "USD",
    "Value": 23.242
  },
  {
    "Name": "CAD",
    "Base": "USD",
    "Value": 1.360855
  },
  {
    "Name": "PLN",
    "Base": "USD",
    "Value": 3.9552519999999998
  }
]