[
  {
    "Name": "EUR",
    "Base": "USD",
    "Value": 0.9181849999999999
  },
  {
    "Name": "TRY",
    "Base": "USD",
    "Value": 33.055800000000005
  },
  {
    "Name": "TRY",
    "Base": "EUR",
    "Value": 35.997110000000006
  },
  {
    "Name": "SAR",
    "Base": "USD",
    "Value": 3.750879
  },
  {
    "Name": "NOK",
    "Base": "USD",
    "Value": 10.7515
  },
  {
    "Name": "JPY",
    "Base": "USD",
    "Value": 158.762
  },
  {
    "Name": "HUF",
    "Base": "USD",
    "Value": 360.476
  },
  {
    "Name": "CZK",
    "Base": "USD",
    "Value": 23.268800000000002
  },
  {
    "Name": "CAD",
    "Base": "USD",
    "Value": 1.36347
  },
  {
    "Name": "PLN",
    "Base": "USD",
    "Value": 3.9101049999999997
  }
]