[
  {
    "Name": "EUR",
    "Base": "USD",
    "Value": 0.92182
  },
  {
    "Name": "TRY",
    "Base": "USD",
    "Value": 32.824200000000005
  },
  {
    "Name": "TRY",
    "Base": "EUR",
    "Value": 35.60966161
  },
  {
    "Name": "SAR",
    "Base": "USD",
    "Value": 3.7511289999999997
  },
  {
    "Name": "NOK",
    "Base": "USD",
    "Value": 11.044260000000001
  },
  {
    "Name": "JPY",
    "Base": "USD",
    "Value": 156.036
  },
  {
    "Name": "HUF",
    "Base": "USD",
    "Value": 360.24
  },
  {
    "Name": "CZK",
    "Base": "USD",
    "Value": 23.424400000000002
  },
  {
    "Name": "CAD",
    "Base": "USD",
    "Value": 1.377
  },
  {
    "Name": "PLN",
    "Base": "USD",
    "Value": 3.94535
  }
]