[
  {
    "Name": "EUR",
    "Base": "USD",
    "Value": 0.93623
  },
  {
    "Name": "TRY",
    "Base": "USD",
    "Value": 28.499800000000004
  },
  {
    "Name": "SAR",
    "Base": "USD",
    "Value": 3.751376
  },
  {
    "Name": "NOK",
    "Base": "USD",
    "Value": 11.21771
  },
  {
    "Name": "JPY",
    "Base": "USD",
    "Value": 150.5025
  },
  {
    "Name": "HUF",
    "Base": "USD",
    "Value": 354.212
  },
  {
    "Name": "CZK",
    "Base": "USD",
    "Value": 23.063000000000002
  },
  {
    "Name": "CAD",
    "Base": "USD",
    "Value": 1.377685
  },
  {
    "Name": "PLN",
    "Base": "USD",
    "Value": 4.17754
  }
]