[
  {
    "Name": "EUR",
    "Base": "USD",
    "Value": 0.91658
  },
  {
    "Name": "TRY",
    "Base": "USD",
    "Value": 33.4994
  },
  {
    "Name": "TRY",
    "Base": "EUR",
    "Value": 36.54258
  },
  {
    "Name": "SAR",
    "Base": "USD",
    "Value": 3.752836
  },
  {
    "Name": "NOK",
    "Base": "USD",
    "Value": 10.858600000000001
  },
  {
    "Name": "JPY",
    "Base": "USD",
    "Value": 147.21200000000002
  },
  {
    "Name": "HUF",
    "Base": "USD",
    "Value": 363.247
  },
  {
    "Name": "CZK",
    "Base": "USD",
    "Value": 23.164
  },
  {
    "Name": "CAD",
    "Base": "USD",
    "Value": 1.374245
  },
  {
    "Name": "PLN",
    "Base": "USD",
    "Value": 3.964905
  }
]