[
  {
    "Name": "EUR",
    "Base": "USD",
    "Value": 0.927315
  },
  {
    "Name": "TRY",
    "Base": "USD",
    "Value": 30.593100000000003
  },
  {
    "Name": "SAR",
    "Base": "USD",
    "Value": 3.750238
  },
  {
    "Name": "NOK",
    "Base": "USD",
    "Value": 10.5777
  },
  {
    "Name": "JPY",
    "Base": "USD",
    "Value": 148.34550000000002
  },
  {
    "Name": "HUF",
    "Base": "USD",
    "Value": 360
  },
  {
    "Name": "CZK",
    "Base": "USD",
    "Value": 23.1396
  },
  {
    "Name": "CAD",
    "Base": "USD",
    "Value": 1.3451499999999998
  },
  {
    "Name": "PLN",
    "Base": "USD",
    "Value": 4.02835
  }
]