[
  {
    "Name": "EUR",
    "Base": "USD",
    "Value": 0.940245
  },
  {
    "Name": "TRY",
    "Base": "USD",
    "Value": 32.49192
  },
  {
    "Name": "SAR",
    "Base": "USD",
    "Value": 3.7511929999999998
  },
  {
    "Name": "NOK",
    "Base": "USD",
    "Value": 10.97202
  },
  {
    "Name": "JPY",
    "Base": "USD",
    "Value": 154.5085
  },
  {
    "Name": "HUF",
    "Base": "USD",
    "Value": 371.182
  },
  {
    "Name": "CZK",
    "Base": "USD",
    "Value": 23.742
  },
  {
    "Name": "CAD",
    "Base": "USD",
    "Value": 1.38205
  },
  {
    "Name": "PLN",
    "Base": "USD",
    "Value": 4.097598
  }
]