[
  {
    "Name": "EUR",
    "Base": "USD",
    "Value": 0.8957299999999999
  },
  {
    "Name": "TRY",
    "Base": "USD",
    "Value": 34.028200000000005
  },
  {
    "Name": "TRY",
    "Base": "EUR",
    "Value": 37.99365
  },
  {
    "Name": "SAR",
    "Base": "USD",
    "Value": 3.752363
  },
  {
    "Name": "NOK",
    "Base": "USD",
    "Value": 10.542440000000001
  },
  {
    "Name": "JPY",
    "Base": "USD",
    "Value": 144.348
  },
  {
    "Name": "HUF",
    "Base": "USD",
    "Value": 353.48
  },
  {
    "Name": "CZK",
    "Base": "USD",
    "Value": 22.443350000000002
  },
  {
    "Name": "CAD",
    "Base": "USD",
    "Value": 1.34825
  },
  {
    "Name": "PLN",
    "Base": "USD",
    "Value": 3.8359959999999997
  }
]