[
  {
    "Name": "EUR",
    "Base": "USD",
    "Value": 0.905155
  },
  {
    "Name": "TRY",
    "Base": "USD",
    "Value": 34.0130039
  },
  {
    "Name": "TRY",
    "Base": "EUR",
    "Value": 37.57656
  },
  {
    "Name": "SAR",
    "Base": "USD",
    "Value": 3.752693
  },
  {
    "Name": "NOK",
    "Base": "USD",
    "Value": 10.69456
  },
  {
    "Name": "JPY",
    "Base": "USD",
    "Value": 145.325602
  },
  {
    "Name": "HUF",
    "Base": "USD",
    "Value": 356.599044
  },
  {
    "Name": "CZK",
    "Base": "USD",
    "Value": 22.7252
  },
  {
    "Name": "CAD",
    "Base": "USD",
    "Value": 1.35527
  },
  {
    "Name": "PLN",
    "Base": "USD",
    "Value": 3.87476751
  }
]