[
  {
    "Name": "EUR",
    "Base": "USD",
    "Value": 0.9180499999999999
  },
  {
    "Name": "TRY",
    "Base": "USD",
    "Value": 33.028000000000006
  },
  {
    "Name": "TRY",
    "Base": "EUR",
    "Value": 35.9478
  },
  {
    "Name": "SAR",
    "Base": "USD",
    "Value": 3.7482439999999997
  },
  {
    "Name": "NOK",
    "Base": "USD",
    "Value": 10.923100000000002
  },
  {
    "Name": "JPY",
    "Base": "USD",
    "Value": 157.51500000000001
  },
  {
    "Name": "HUF",
    "Base": "USD",
    "Value": 359.03000000000003
  },
  {
    "Name": "CZK",
    "Base": "USD",
    "Value": 23.180500000000002
  },
  {
    "Name": "CAD",
    "Base": "USD",
    "Value": 1.3771499999999999
  },
  {
    "Name": "PLN",
    "Base": "USD",
    "Value": 3.9352709999999997
  }
]