[
  {
    "Name": "EUR",
    "Base": "USD",
    "Value": 0.9204549999999999
  },
  {
    "Name": "TRY",
    "Base": "USD",
    "Value": 30.1277
  },
  {
    "Name": "SAR",
    "Base": "USD",
    "Value": 3.750409
  },
  {
    "Name": "NOK",
    "Base": "USD",
    "Value": 10.53386
  },
  {
    "Name": "JPY",
    "Base": "USD",
    "Value": 148.2795
  },
  {
    "Name": "HUF",
    "Base": "USD",
    "Value": 350.29900000000004
  },
  {
    "Name": "CZK",
    "Base": "USD",
    "Value": 22.761000000000003
  },
  {
    "Name": "CAD",
    "Base": "USD",
    "Value": 1.352755
  },
  {
    "Name": "PLN",
    "Base": "USD",
    "Value": 4.04765
  }
]