[
  {
    "Name": "EUR",
    "Base": "USD",
    "Value": 0.95526
  },
  {
    "Name": "TRY",
    "Base": "USD",
    "Value": 27.542700000000004
  },
  {
    "Name": "SAR",
    "Base": "USD",
    "Value": 3.750514
  },
  {
    "Name": "NOK",
    "Base": "USD",
    "Value": 10.96358
  },
  {
    "Name": "JPY",
    "Base": "USD",
    "Value": 149.17100000000002
  },
  {
    "Name": "HUF",
    "Base": "USD",
    "Value": 373.30400000000003
  },
  {
    "Name": "CZK",
    "Base": "USD",
    "Value": 23.416800000000002
  },
  {
    "Name": "CAD",
    "Base": "USD",
    "Value": 1.369745
  },
  {
    "Name": "PLN",
    "Base": "USD",
    "Value": 4.425549999999999
  }
]