[
  {
    "Name": "EUR",
    "Base": "USD",
    "Value": 0.95088
  },
  {
    "Name": "TRY",
    "Base": "USD",
    "Value": 27.80148
  },
  {
    "Name": "SAR",
    "Base": "USD",
    "Value": 3.751137
  },
  {
    "Name": "NOK",
    "Base": "USD",
    "Value": 10.951440000000002
  },
  {
    "Name": "JPY",
    "Base": "USD",
    "Value": 149.6095
  },
  {
    "Name": "HUF",
    "Base": "USD",
    "Value": 368.803
  },
  {
    "Name": "CZK",
    "Base": "USD",
    "Value": 23.4643
  },
  {
    "Name": "CAD",
    "Base": "USD",
    "Value": 1.3684349999999998
  },
  {
    "Name": "PLN",
    "Base": "USD",
    "Value": 4.319464
  }
]