[
  {
    "Name": "EUR",
    "Base": "USD",
    "Value": 0.9218
  },
  {
    "Name": "TRY",
    "Base": "USD",
    "Value": 33.1152
  },
  {
    "Name": "TRY",
    "Base": "EUR",
    "Value": 35.92436241
  },
  {
    "Name": "SAR",
    "Base": "USD",
    "Value": 3.7515899999999998
  },
  {
    "Name": "NOK",
    "Base": "USD",
    "Value": 11.030880000000002
  },
  {
    "Name": "JPY",
    "Base": "USD",
    "Value": 153.6175
  },
  {
    "Name": "HUF",
    "Base": "USD",
    "Value": 361.855
  },
  {
    "Name": "CZK",
    "Base": "USD",
    "Value": 23.3885
  },
  {
    "Name": "CAD",
    "Base": "USD",
    "Value": 1.3823649999999998
  },
  {
    "Name": "PLN",
    "Base": "USD",
    "Value": 3.95178
  }
]