[
  {
    "Name": "EUR",
    "Base": "USD",
    "Value": 0.913115
  },
  {
    "Name": "TRY",
    "Base": "USD",
    "Value": 28.910100000000003
  },
  {
    "Name": "SAR",
    "Base": "USD",
    "Value": 3.7503879999999996
  },
  {
    "Name": "NOK",
    "Base": "USD",
    "Value": 10.673530000000001
  },
  {
    "Name": "JPY",
    "Base": "USD",
    "Value": 149.041
  },
  {
    "Name": "HUF",
    "Base": "USD",
    "Value": 347.011
  },
  {
    "Name": "CZK",
    "Base": "USD",
    "Value": 22.250500000000002
  },
  {
    "Name": "CAD",
    "Base": "USD",
    "Value": 1.36293
  },
  {
    "Name": "PLN",
    "Base": "USD",
    "Value": 3.976086
  }
]